pynject/__init__.py
pynject/builders.py
pynject/const.py
pynject/decorators.py
pynject/helpers.py
pynject/injector.py
pynject/model.py
pynject/module.py
Pynject-0.4.2.dist-info/LICENSE
Pynject-0.4.2.dist-info/METADATA
Pynject-0.4.2.dist-info/WHEEL
Pynject-0.4.2.dist-info/top_level.txt
Pynject-0.4.2.dist-info/RECORD
