Metadata-Version: 2.1
Name: Pynject
Version: 0.4.2
Summary: A minimalist python injector
Home-page: https://github.com/JGiard/Pynject
Author: Jean Giard
Author-email: opensource@antidot.net
License: LGPL-2.1-or-later
Keywords: pynject json
License-File: LICENSE
